temp_mails/__init__.py
temp_mails/_constructors.py
temp_mails/providers/adguard_com.py
temp_mails/providers/anonymmail_net.py
temp_mails/providers/burnermailbox_com.py
temp_mails/providers/byom_de.py
temp_mails/providers/cloudtempmail_com.py
temp_mails/providers/correotemporal_org.py
temp_mails/providers/crazymailing_com.py
temp_mails/providers/cryptogmail_com.py
temp_mails/providers/disposableemail_co.py
temp_mails/providers/disposablemail_com.py
temp_mails/providers/dropmail_me.py
temp_mails/providers/emaildashfake_com.py
temp_mails/providers/emaildashfree_online.py
temp_mails/providers/emailfake_com.py
temp_mails/providers/emailondeck_com.py
temp_mails/providers/emailtenmin_com.py
temp_mails/providers/etempmail_com.py
temp_mails/providers/etempmail_net.py
temp_mails/providers/expressinboxhub_com.py
temp_mails/providers/eyepaste_com.py
temp_mails/providers/eztempmail_com.py
temp_mails/providers/fakemail_net.py
temp_mails/providers/fakemailgenerator_com.py
temp_mails/providers/fakermail_com.py
temp_mails/providers/fmail_sbs.py
temp_mails/providers/fumail_co.py
temp_mails/providers/generator_email.py
temp_mails/providers/getnada_cc.py
temp_mails/providers/gmailcity_com.py
temp_mails/providers/guerillamail_com.py
temp_mails/providers/harakirimail_com.py
temp_mails/providers/haribu_net.py
temp_mails/providers/inboxes_com.py
temp_mails/providers/inboxkitten_com.py
temp_mails/providers/incognitomail_co.py
temp_mails/providers/internxt_com.py
temp_mails/providers/lroid_com.py
temp_mails/providers/luxusmail_org.py
temp_mails/providers/maidashtemp_com.py
temp_mails/providers/mail_gw.py
temp_mails/providers/mail_td.py
temp_mails/providers/mail_tm.py
temp_mails/providers/mailcatch_com.py
temp_mails/providers/maildax_com.py
temp_mails/providers/mailforspam_com.py
temp_mails/providers/mailfourqa_com.py
temp_mails/providers/mailgolem_com.py
temp_mails/providers/mailhole_de.py
temp_mails/providers/mailinator_com.py
temp_mails/providers/maillog_org.py
temp_mails-2.2.0.dist-info/METADATA
temp_mails-2.2.0.dist-info/WHEEL
temp_mails-2.2.0.dist-info/licenses/LICENSE
temp_mails-2.2.0.dist-info/RECORD
