Metadata-Version: 2.4
Name: temp-mails
Version: 2.2.0
Summary: A basic wrapper around various temp mail sites, aiming to provide an almost identical api for every site. The main purpose of this is to provide an easy way to quickly register an account on various sites and then discard the email.
Project-URL: Homepage, https://github.com/bertigert/temp-mails
Project-URL: Issues, https://github.com/bertigert/temp-mails/issues
Author-email: bertigert <bertiger@riseup.net>
License-File: LICENSE
Classifier: License :: OSI Approved :: MIT License
Classifier: Operating System :: OS Independent
Classifier: Programming Language :: Python :: 3
Requires-Python: >=3.8
